hs_build_tools/__init__.py
hs_build_tools/assert_text_template.py
hs_build_tools/nose.py
hs_build_tools/pytest.py
hs_build_tools/pyz.py
hs_build_tools/release.py
hs_build_tools/runenv.py
hs_build_tools/tidy.py
hs_build_tools-2021.10.dist-info/LICENSE
hs_build_tools-2021.10.dist-info/METADATA
hs_build_tools-2021.10.dist-info/WHEEL
hs_build_tools-2021.10.dist-info/entry_points.txt
hs_build_tools-2021.10.dist-info/top_level.txt
hs_build_tools-2021.10.dist-info/zip-safe
hs_build_tools-2021.10.dist-info/RECORD
